Jogo/Jogo.py
Jogo/JogoController.py
Jogo/__init__.py
Tabuleiro/__init__.py
Tabuleiro/cpu.py
Tabuleiro/jogador.py
Tabuleiro/tabuleiro.py
JogoDaVelha_Elielson68-0.0.3.dist-info/LICENSE
JogoDaVelha_Elielson68-0.0.3.dist-info/METADATA
JogoDaVelha_Elielson68-0.0.3.dist-info/WHEEL
JogoDaVelha_Elielson68-0.0.3.dist-info/top_level.txt
JogoDaVelha_Elielson68-0.0.3.dist-info/RECORD
