Metadata-Version: 2.1
Name: JogoDaVelha-Elielson68
Version: 0.0.3
Summary: is a simples 'jogo da velha' game
Home-page: https://github.com/Elielson68/JogoDaVelha
Author: Elielson Barbosa
Author-email: elielsonbr.com@gmail.com
License: UNKNOWN
Platform: UNKNOWN
Classifier: Programming Language :: Python :: 3
Classifier: License :: OSI Approved :: MIT License
Classifier: Operating System :: OS Independent
Requires-Python: >=3.6
